acscsv/__init__.py
acscsv/acscsv.py
acscsv/custom_output.py
acscsv/disqus_acs.py
acscsv/reflect_json.py
acscsv/snowflake.py
acscsv/test_acscsv.py
acscsv/test_disqus_acs.py
acscsv/test_foursquare_acs.py
acscsv/test_newsgator_acs.py
acscsv/test_reflect_json.py
acscsv/test_snowflake.py
acscsv/test_stocktwits_acs.py
acscsv/test_stocktwits_native.py
acscsv/test_tumblr_acs.py
acscsv/test_twitter_acs.py
acscsv/test_wordpress_acs.py
acscsv/twitter_acs.py
acscsv/twitter_acs_fields.py
acscsv/wordpress_acs.py
gnacsupdated-1.0.1.data/scripts/gnacs.py
gnacsupdated-1.0.1.dist-info/DESCRIPTION.rst
gnacsupdated-1.0.1.dist-info/METADATA
gnacsupdated-1.0.1.dist-info/RECORD
gnacsupdated-1.0.1.dist-info/WHEEL
gnacsupdated-1.0.1.dist-info/metadata.json
gnacsupdated-1.0.1.dist-info/top_level.txt
