Metadata-Version: 2.0
Name: gnacsupdated
Version: 1.0.1
Summary: Gnip normalized activity JSON to csv parser (Twitter, Disqus Comments, and Wordpress Posts and Comments)
Home-page: https://github.com/nikhilsu/Gnacs
Author: Scott Hendrickson, Josh Montague, Jinsub Hong, Jeff Kolb, Brian Lehman, Fiona Pigott, Nikhil Sulegaon
Author-email: nikhilsulegaon@gmail.com
License: LICENSE.txt
Download-URL: https://github.com/nikhilsu/Gnacs/tags/1.0.1
Platform: UNKNOWN
Requires-Dist: ujson (>=1.2)
